{
  "id": "task_1783544276279_3802",
  "subject": "Boxue/gewu: Design falsifiable validation protocol",
  "description": "Boxue delegation plan: boxue_1783544276054964400\nProject: 全钒液流电池 AutoGen 多Agent协作闭环验证 (sci_1783544267561342700)\nDomain: Vanadium Redox Flow Battery / Energy Storage / Electrochemical Engineering\nProject objective: 验证全钒液流电池领域中，基于文献证据的 gap 发现、假设生成、机制检验和辩论迭代闭环。\nRound goal: 围绕全钒液流电池，系统阅读高影响综述、里程碑电极材料与隔膜、最新顶刊关于性能衰减、容量恢复、电解液稳定性、高功率密度设计成果和相关预印本，构建 PaperGraph，识别真实机制 gap，生成可证伪科学假设，并通过 YanZhen 机制一致性检验与 DuZhi/BianLun 苏格拉底辩论进行迭代。\nAssigned agent: gewu\nPhase: Experimental Design\nPriority: high\nAllowed/expected tools: design_experiment, define_baselines, define_metrics\n\nTask:\nTranslate verified hypotheses into executable experiments with baselines and metrics.\n\nDeliverable:\nExperiment protocol with datasets, baselines, metrics, controls, and falsification criteria.\n\nAcceptance criteria:\n- At least one standard and one strong baseline\n- Metrics have success thresholds\n- Falsification criteria are stated before execution\n\nKnown risks to handle:\n- insufficient baseline\n- unreproducible protocol\n\nRole boundary: complete only this specialist responsibility. Do not take over Boxue coordination, do not invent evidence, and mark unsupported claims for review.\nOutput should be compact structured JSON suitable for downstream agents.\n",
  "status": "pending",
  "owner": null,
  "worktree": null,
  "blockedBy": [
    "task_1783544276239_8887"
  ],
  "createdAt": 1783544276.2792103,
  "updatedAt": 1783544276.315791
}