{
  "id": "task_1783678792981_9176",
  "subject": "Boxue/bianlun: Moderate structured debate and synthesize refined hypothesis",
  "description": "Boxue delegation plan: boxue_1783678792862492300\nProject: 4.5V以上高压锂电池机制与稳定性研究 (sci_1783678774790450900)\nDomain: High-voltage lithium batteries above 4.5 V\nProject objective: 从高质量文献中识别高电压运行下正极结构退化、界面副反应、氧释放、电解液氧化、容量衰减和安全性之间的机制缺口，生成可验证且可修订的研究假设。\nRound goal: 从高质量文献中识别高电压运行下正极结构退化、界面副反应、氧释放、电解液氧化、容量衰减和安全性之间的机制缺口，生成可验证且可修订的研究假设。\nAssigned agent: bianlun\nPhase: Socratic Debate\nPriority: medium\nAllowed/expected tools: run_socratic_hypothesis_debate, moderate_round, summarize_positions, extract_emergent_method\n\nTask:\nIntegrate proposer and critic positions, identify disagreements, and produce refined hypotheses.\n\nDeliverable:\nDebate record with convergence points, unresolved issues, and emergent methods.\n\nAcceptance criteria:\n- Arguments are separated into factual vs conceptual disagreements\n- Refined hypothesis lists improvements from critique\n- Remaining risks are explicit\n\nKnown risks to handle:\n- false consensus\n- debate loops without synthesis\n\nRole boundary: complete only this specialist responsibility. Do not take over Boxue coordination, do not invent evidence, and mark unsupported claims for review.\nOutput should be compact structured JSON suitable for downstream agents.\n",
  "status": "pending",
  "owner": null,
  "blockedBy": [
    "task_1783678792953_9739"
  ],
  "createdAt": 1783678792.98113,
  "updatedAt": 1783678793.0062463
}